{
  "id": "floor-1",
  "name": "1F 入口大厅",
  "width": 416,
  "height": 416,
  "tileWidth": 32,
  "tileHeight": 32,
  "spriteSheets": ["tower-tiles", "characters", "items", "ui"],
  "layers": [
    {
      "name": "tiles",
      "type": "tile",
      "spriteSheet": "tower-tiles",
      "encoding": "names",
      "data": [
        "wall_gray","wall_gray","wall_gray","wall_gray","wall_gray","wall_gray","stair_up","wall_gray","wall_gray","wall_gray","wall_gray","wall_gray","wall_gray",
        "wall_gray","floor_stone","floor_stone","floor_stone","wall_gray","floor_stone","floor_stone","floor_stone","wall_gray","floor_stone","floor_stone","floor_stone","wall_gray",
        "wall_gray","floor_stone","wall_gray","floor_stone","wall_gray","floor_stone","wall_gray","floor_stone","wall_gray","floor_stone","wall_gray","floor_stone","wall_gray",
        "wall_gray","floor_stone","wall_gray","floor_stone","floor_stone","floor_stone","wall_gray","floor_stone","floor_stone","floor_stone","wall_gray","floor_stone","wall_gray",
        "wall_gray","floor_stone","wall_gray","wall_gray","wall_gray","door_yellow","wall_gray","door_yellow","wall_gray","wall_gray","wall_gray","floor_stone","wall_gray",
        "wall_gray","floor_stone","floor_stone","floor_stone","floor_stone","floor_stone","floor_stone","floor_stone","floor_stone","floor_stone","floor_stone","floor_stone","wall_gray",
        "wall_gray","torch","wall_gray","wall_gray","wall_gray","floor_stone","wall_gray","floor_stone","wall_gray","wall_gray","wall_gray","torch","wall_gray",
        "wall_gray","floor_stone","floor_stone","floor_stone","wall_gray","floor_stone","wall_gray","floor_stone","wall_gray","floor_stone","floor_stone","floor_stone","wall_gray",
        "wall_gray","floor_stone","wall_gray","floor_stone","wall_gray","floor_stone","wall_gray","floor_stone","wall_gray","floor_stone","wall_gray","floor_stone","wall_gray",
        "wall_gray","floor_stone","wall_gray","floor_stone","floor_stone","floor_stone","floor_stone","floor_stone","floor_stone","floor_stone","wall_gray","floor_stone","wall_gray",
        "wall_gray","floor_stone","wall_gray","wall_gray","wall_gray","wall_gray","floor_stone","wall_gray","wall_gray","wall_gray","wall_gray","floor_stone","wall_gray",
        "wall_gray","floor_stone","floor_stone","floor_stone","floor_stone","floor_stone","floor_stone","floor_stone","floor_stone","floor_stone","floor_stone","floor_stone","wall_gray",
        "wall_gray","wall_gray","wall_gray","wall_gray","wall_gray","wall_gray","wall_gray","wall_gray","wall_gray","wall_gray","wall_gray","wall_gray","wall_gray"
      ]
    },
    {
      "name": "entities",
      "type": "entity",
      "entities": [
        {
          "id": "f1_player",
          "template": "player",
          "name": "勇者",
          "x": 192,
          "y": 352,
          "width": 32,
          "height": 32,
          "fields": { "direction": "up" }
        },
        {
          "id": "f1_stair_up",
          "template": "stair",
          "name": "上楼梯",
          "x": 192,
          "y": 0,
          "width": 32,
          "height": 32,
          "fields": { "direction": "up", "targetFloor": "floor-2", "targetX": 32, "targetY": 352 }
        },
        {
          "id": "f1_npc_oldman",
          "template": "npc",
          "name": "老人",
          "x": 160,
          "y": 352,
          "width": 32,
          "height": 32,
          "fields": { "npcType": "oldman", "dialog": "欢迎来到魔塔，勇者！收集钥匙打开门，击败怪物收集金币。小心选择战斗对象，注意查看怪物手册！" }
        },
        {
          "id": "f1_slime_1",
          "template": "monster",
          "name": "绿色史莱姆",
          "x": 160,
          "y": 160,
          "width": 32,
          "height": 32,
          "fields": { "monsterType": "slime_green", "hp": 50, "atk": 20, "def": 1, "gold": 1, "exp": 1, "tags": "slime", "boss": false }
        },
        {
          "id": "f1_slime_2",
          "template": "monster",
          "name": "绿色史莱姆",
          "x": 224,
          "y": 160,
          "width": 32,
          "height": 32,
          "fields": { "monsterType": "slime_green", "hp": 50, "atk": 20, "def": 1, "gold": 1, "exp": 1, "tags": "slime", "boss": false }
        },
        {
          "id": "f1_slime_3",
          "template": "monster",
          "name": "绿色史莱姆",
          "x": 192,
          "y": 288,
          "width": 32,
          "height": 32,
          "fields": { "monsterType": "slime_green", "hp": 50, "atk": 20, "def": 1, "gold": 1, "exp": 1, "tags": "slime", "boss": false }
        },
        {
          "id": "f1_door_y1",
          "template": "door",
          "name": "黄门",
          "x": 160,
          "y": 128,
          "width": 32,
          "height": 32,
          "fields": { "color": "yellow" }
        },
        {
          "id": "f1_door_y2",
          "template": "door",
          "name": "黄门",
          "x": 224,
          "y": 128,
          "width": 32,
          "height": 32,
          "fields": { "color": "yellow" }
        },
        {
          "id": "f1_key_y1",
          "template": "key",
          "name": "黄钥匙",
          "x": 96,
          "y": 96,
          "width": 32,
          "height": 32,
          "fields": { "itemType": "key", "color": "yellow" }
        },
        {
          "id": "f1_key_y2",
          "template": "key",
          "name": "黄钥匙",
          "x": 288,
          "y": 96,
          "width": 32,
          "height": 32,
          "fields": { "itemType": "key", "color": "yellow" }
        },
        {
          "id": "f1_key_y3",
          "template": "key",
          "name": "黄钥匙",
          "x": 32,
          "y": 352,
          "width": 32,
          "height": 32,
          "fields": { "itemType": "key", "color": "yellow" }
        },
        {
          "id": "f1_potion_r1",
          "template": "potion",
          "name": "红血瓶",
          "x": 96,
          "y": 224,
          "width": 32,
          "height": 32,
          "fields": { "itemType": "potion", "amount": 100 }
        },
        {
          "id": "f1_potion_r2",
          "template": "potion",
          "name": "红血瓶",
          "x": 288,
          "y": 224,
          "width": 32,
          "height": 32,
          "fields": { "itemType": "potion", "amount": 100 }
        },
        {
          "id": "f1_monster_book",
          "template": "special_item",
          "name": "怪物手册",
          "x": 320,
          "y": 160,
          "width": 32,
          "height": 32,
          "fields": { "itemType": "special", "specialId": "monster_book" }
        }
      ]
    }
  ]
}
